{
"a":{"path":"./2/a.wav"},
"b":{"path":"./2/b.wav"},
"c":{"path":"./2/c.wav"},
"d":{"path":"./2/d.wav"},
"e":{"path":"./2/e.wav"},
"f":{"path":"./2/f.wav"},
"g":{"path":"./2/g.wav"},
"h":{"path":"./2/h.wav"},
"i":{"path":"./2/i.wav"},
"j":{"path":"./2/j.wav"},
"k":{"path":"./2/k.wav"},
"l":{"path":"./2/l.wav"},
"m":{"path":"./2/m.wav"},
"n":{"path":"./2/n.wav"},
"o":{"path":"./2/o.wav"},
"p":{"path":"./2/p.wav"},
"q":{"path":"./2/q.wav"},
"r":{"path":"./2/r.wav"},
"s":{"path":"./2/s.wav"},
"sh":{"path":"./2/sh.wav"},
"t":{"path":"./2/t.wav"},
"th":{"path":"./2/th.wav"},
"u":{"path":"./2/u.wav"},
"v":{"path":"./2/v.wav"},
"w":{"path":"./2/w.wav"},
"x":{"path":"./2/x.wav"},
"y":{"path":"./2/y.wav"},
"z":{"path":"./2/z.wav"},
}
